arf_tools/__init__.py
arf_tools/main.py
arf_tools/data/USPS_test.txt
arf_tools/data/USPS_train.txt
arf_tools/data/imdb_extrait.pkl
arf_tools/data/poi-paris.pkl
arf_tools/res/global_variables.json
arf_tools/res/paris-48.806-2.23--48.916-2.48.jpg
arf_tools/src/__init__.py
arf_tools/src/accuracy_evaluation.py
arf_tools/src/data_generation.py
arf_tools/src/display.py
arf_tools/src/parse_data.py
arf_tools/src/splitting.py
arf_tools/src/useless_functions.py
arf_tools/src/classifiers/__init__.py
arf_tools/src/classifiers/classifier.py
arf_tools/src/classifiers/decision_tree.py
arf_tools/src/classifiers/density_estimation.py
arf_tools/src/classifiers/logistic_regression.py
arf_tools/src/classifiers/naive_bayes.py
arf_tools/src/classifiers/perceptron.py
arf_tools/src/classifiers/random.py
arf_tools/src/classifiers/utils/__init__.py
arf_tools/src/classifiers/utils/cost_function.py
arf_tools/src/classifiers/utils/gradient_descent.py
arf_tools/src/classifiers/utils/kernels.py
arf_tools/src/classifiers/utils/projection.py
arf_tools/src/classifiers/utils/string_kernel.py
arf_tools/src/getters/__init__.py
arf_tools/src/getters/get_global_variable.py
arf_tools-1.0.0.dist-info/DESCRIPTION.rst
arf_tools-1.0.0.dist-info/METADATA
arf_tools-1.0.0.dist-info/RECORD
arf_tools-1.0.0.dist-info/WHEEL
arf_tools-1.0.0.dist-info/metadata.json
arf_tools-1.0.0.dist-info/top_level.txt
