Metadata-Version: 2.0
Name: arf-tools
Version: 1.0.0
Summary: Machine learning tools builded during the ARF class, from Sorbonne Université
Home-page: https://github.com/NicolasBizzozzero/arf-tools
Author: Bizzozzéro Nicolas, Adoum Robert
Author-email: nicolasbizzozzero@gmail.com
License: GPL-3.0
Download-URL: https://github.com/NicolasBizzozzero/arf-tools/tarball/master
Keywords: machine-learning,classification
Platform: UNKNOWN
Classifier: Development Status :: 5 - Production/Stable
Classifier: Natural Language :: French
Classifier: Intended Audience :: Education
Classifier: Topic :: Education
Classifier: Topic :: Scientific/Engineering :: Artificial Intelligence
Classifier: Topic :: Software Development :: Libraries :: Python Modules
Classifier: License :: OSI Approved :: GNU General Public License v3 (GPLv3)
Classifier: Programming Language :: Python :: 3.4
Requires-Dist: matplotlib (>=2.2.2)
Requires-Dist: numpy (>=1.14.2)
Requires-Dist: seaborn (>=0.8.1)
Requires-Dist: scikit-learn (>=0.19.1)
